{
  "$schema": "https://json-schema.org/draft/2020-12/schema",
  "$id": "../forms/econ.fin.exchange.json",
  "title": "exchange",
  "description": "A sample of the price of a security at a single moment in time",
  "properties": {
    "name": {
      "description": "A simple name for the exchange",
      "type": "string"
    },
    "org": {
      "description": "The organization that operates the exchange",
      "$ref": "../forms/ou.org.json"
    },
    "currency": {
      "description": "The currency used for all transactions in the exchange",
      "$ref": "../forms/econ.currency.json"
    }
  },
  "type": "object"
}